velocitypgmdata/__init__.py
velocitypgmdata/machine_condition.py
velocitypgmdata-0.2.dist-info/METADATA
velocitypgmdata-0.2.dist-info/WHEEL
velocitypgmdata-0.2.dist-info/top_level.txt
velocitypgmdata-0.2.dist-info/RECORD
